scripts/__init__.py
scripts/get_script.py
scripts/custom/__init__.py
scripts/custom/clean_address.py
scripts/custom/clean_date.py
scripts/custom/clean_phone.py
scripts/custom/map_deceased.py
scripts/custom/map_family_situation.py
scripts/custom/map_gender.py
scripts/custom/map_gender_numeric.py
scripts/custom/map_numeric_boolean.py
scripts/custom/map_status.py
scripts/custom/merge_insee.py
scripts/logic/__init__.py
scripts/logic/careplan_intent_classif.py
scripts/logic/careplan_status_classif.py
scripts/logic/if_valid.py
scripts/logic/map_careplan_intent.py
scripts/logic/map_careplan_status.py
scripts/utils/__init__.py
scripts/utils/is_empty.py
scripts/utils/make_title.py
scripts/utils/merge_concat.py
scripts/utils/merge_datetime.py
scripts/utils/select_first_not_empty.py
scripts/utils/strip.py
cleaning_scripts-0.2.2.dist-info/LICENSE
cleaning_scripts-0.2.2.dist-info/METADATA
cleaning_scripts-0.2.2.dist-info/WHEEL
cleaning_scripts-0.2.2.dist-info/top_level.txt
cleaning_scripts-0.2.2.dist-info/RECORD
