Metadata-Version: 2.1
Name: cleaning-scripts
Version: 0.2.2
Summary: Python scripts used in the FHIR integration pipeline to clean input data for different external sources.
Home-page: https://github.com/arkhn/cleaning-scripts
Author: Arkhn
Author-email: contact@arkhn.org
License: Apache License 2.0
Platform: UNKNOWN
Requires-Dist: requests (==2.21.0)
Requires-Dist: WTForms (==2.2.1)
Requires-Dist: Flask-WTF (==0.14.2)
Requires-Dist: Flask (==1.1.1)
Requires-Dist: Flask-Cors (==3.0.8)
Requires-Dist: python-dotenv (==0.10.3)
Requires-Dist: GitPython (==3.0.2)
Requires-Dist: PyGithub (==1.43.8)
